burmese_tools/__init__.py
burmese_tools/main.py
burmese_tools-0.1.2.dist-info/LICENSE
burmese_tools-0.1.2.dist-info/METADATA
burmese_tools-0.1.2.dist-info/WHEEL
burmese_tools-0.1.2.dist-info/top_level.txt
burmese_tools-0.1.2.dist-info/RECORD
