Metadata-Version: 2.1
Name: burmese-tools
Version: 0.1.2
Summary: Burmese NLP Tools
Home-page: https://github.com/MinThihaTun3012/burmese_tools/tree/main
Author: Min Thiha Tun
Author-email: mtht1794@gmail.com
License: MIT
Classifier: Programming Language :: Python :: 3
Classifier: License :: OSI Approved :: MIT License
Classifier: Operating System :: OS Independent
Requires-Python: >=3.6
License-File: LICENSE
